blackboxprotobuf/__init__.py
blackboxprotobuf/__main__.py
blackboxprotobuf/lib/__init__.py
blackboxprotobuf/lib/api.py
blackboxprotobuf/lib/config.py
blackboxprotobuf/lib/exceptions.py
blackboxprotobuf/lib/payloads/__init__.py
blackboxprotobuf/lib/payloads/grpc.py
blackboxprotobuf/lib/payloads/gzip.py
blackboxprotobuf/lib/protofile.py
blackboxprotobuf/lib/pytypes.py
blackboxprotobuf/lib/typedef.py
blackboxprotobuf/lib/types/__init__.py
blackboxprotobuf/lib/types/fixed.py
blackboxprotobuf/lib/types/length_delim.py
blackboxprotobuf/lib/types/type_maps.py
blackboxprotobuf/lib/types/varint.py
blackboxprotobuf/lib/types/wiretypes.py
blackboxprotobuf/py.typed
bbpb-1.4.0.dist-info/METADATA
bbpb-1.4.0.dist-info/WHEEL
bbpb-1.4.0.dist-info/entry_points.txt
bbpb-1.4.0.dist-info/RECORD
