Metadata-Version: 2.1
Name: bbpb
Version: 1.4.0
Summary: Library for working with protobuf messages without a protobuf type definition.
Home-page: https://github.com/nccgroup/blackboxprotobuf
License: MIT
Keywords: protobuf
Author: Ryan Winkelmaier
Author-email: ryan.winkelmaier@nccgroup.com
Requires-Python: >=3.8,<4.0
Classifier: License :: OSI Approved :: MIT License
Classifier: Programming Language :: Python :: 3
Classifier: Programming Language :: Python :: 3.8
Classifier: Programming Language :: Python :: 3.9
Classifier: Programming Language :: Python :: 3.10
Classifier: Programming Language :: Python :: 3.11
Classifier: Programming Language :: Python :: 3.12
Requires-Dist: six (>=1.16,<2.0)
Project-URL: Repository, https://github.com/nccgroup/blackboxprotobuf
